{
  "dates": [
    "2026-04-17",
    "2026-04-14",
    "2026-04-13"
  ],
  "latest_day": "2026-04-17",
  "competitors_on_day": [
    {
      "session_id": 19,
      "competitor": "一本官方旗舰店",
      "recorded_at": "2026-04-17 23:53:31.370653",
      "key_products": [
        {
          "name": "一本官方旗舰店·语文+英语两本书",
          "price": "54元（半价）",
          "selling_points": [
            "包含小学六年+初中九年54篇文言文+87首古诗词",
            "包含小学六年+初中三年2000个新课标单词",
            "赠送动画视频、漫画图解、思维导图",
            "纯正外教音频发音+拼读助记+漫画助记",
            "全程老师打卡监督（仅直播间购买享有）",
            "打卡成功送小奖牌包邮"
          ],
          "scripts": [
            {
              "type": "开场/暖场",
              "content": "听明白了可以去下单了，拍完记得回来留语拍，然后拍下一号链接两本的",
              "timestamp": "[00:00 --> 00:05]"
            },
            {
              "type": "痛点",
              "content": "接下来五一假期包括春假然后暑假，你要知道假期真的非常多你这个天气玩肯定是不行的，该备的怎么备，假期加了没时间监督的，来全程老师打卡监督",
              "timestamp": "[00:06 --> 00:21]"
            },
            {
              "type": "价值塑造",
              "content": "这套是会有全程老师打卡建筑回到家你看到了吗把它贴在墙上就可以了全程老师带着孩子有这个要求去打卡然后打卡被送成功之后有这个小奖牌是免费包邮送的",
              "timestamp": "[00:27 --> 00:41]"
            },
            {
              "type": "产品介绍-语文",
              "content": "一到六年级都可以买的小学生都可以买如果说你想提前背一背一二年级也可以去用因为这套书你能用九年它里面包含到的是整个小学六年加初中三年的五十四天文言玩加八十七首古诗词都是金课标要求孩子们要考要背的都给你做好了标注非常非常全",
              "timestamp": "[01:48 --> 02:09]"
            },
            {
              "type": "产品介绍-学习方法",
              "content": "有动画片有动画片今年给大家新加了动画视频让孩子像看动画圈一样更感兴趣喜欢去背喜欢去学。今天买的这个动画视频动画圈全部都是免费看免费送的。然后第二个我们有什么漫画图解把我的课本去背你干巴巴的死性背肯定记不住背完就忘了漫画全文翻译给你带着那孩子背起来是不是更加简单",
              "timestamp": "[02:18 --> 02:49]"
            },
            {
              "type": "产品介绍-英语",
              "content": "这个是我们今年刚出的新书所以它升级的越来越好了这本书里面给大家整理到的是整个小学六年加初中三年新课标要求孩子们要备要考的2000个单词就更全一些",
              "timestamp": "[03:13 --> 03:24]"
            },
            {
              "type": "价值塑造",
              "content": "有纯正的外教音频发音我们是纯正外教代读这个都是花了钱的今年全部送了",
              "timestamp": "[03:27 --> 03:35]"
            },
            {
              "type": "促销逼单",
              "content": "今年的新版两本半价54我们一本官方直播间保证正品保证售后活动结束100多",
              "timestamp": "[03:50 --> 03:54]"
            },
            {
              "type": "服务保障",
              "content": "这个活动只有在我们直播间拍了送其他任何地方买都没有",
              "timestamp": "[04:19 --> 04:23]"
            }
          ]
        }
      ],
      "user_persona": "3-6年级学生家长，孩子即将面临五一假期、春假和暑假，家长担心假期孩子学习无人监督，希望提前让孩子背诵文言文和英语单词，为初中学习做准备。",
      "strategy_summary": "通过强调假期多、孩子学习无人监督的痛点，引入全程老师打卡监督的独家服务吸引家长；突出产品包含9年学习内容、动画视频、漫画图解等附加价值，塑造产品性价比；利用半价优惠和仅直播间享有的打卡服务进行促销逼单。",
      "highlights": [
        "全程老师打卡监督服务仅直播间购买享有，是核心差异化卖点",
        "产品覆盖小学+初中9年内容，一套书可以用九年",
        "赠送动画视频、漫画图解、思维导图等附加学习资源，提升产品吸引力",
        "价格锚点：半价54元vs活动结束100多元，强调限时优惠"
      ]
    },
    {
      "session_id": 20,
      "competitor": "一本小学好物推荐",
      "recorded_at": "2026-04-17 23:53:31.867596",
      "key_products": [
        {
          "name": "一本·小学期末复习试卷套装（语文+数学+英语三科）",
          "price": "51元三科",
          "selling_points": [
            "三科套装包含单元卷、专项卷、真题压题卷",
            "免费视频讲解二维码，家长无需辅导",
            "赠送考点资料（李淑英三颗考点）",
            "多版本可选：语文全国通用/数学人教苏教北师/英语人教PEP",
            "活动价51元，原价一百多"
          ],
          "scripts": [
            {
              "type": "开场暖场",
              "content": "51块钱活动休息一波",
              "timestamp": "[00:00 --> 00:01]"
            },
            {
              "type": "痛点需求",
              "content": "现在我们还有不到两周，孩子们就要参加期中考试了五一假期结束一回来，再学上一个多月，又要期末考试了这个学期学的时间真的很短，老师们都在赶进度，没时间带着孩子们做总复习",
              "timestamp": "[01:08 --> 01:22]"
            },
            {
              "type": "价值塑造",
              "content": "首先带回家之后，先带着孩子们咱去做我们的单元卷咱得查漏补缺因为期末考试要考课本八个单元所有的内容",
              "timestamp": "[01:33 --> 01:48]"
            },
            {
              "type": "效果承诺",
              "content": "现在前四个单元的内容咱已经学完了期中考试就考到这咱把前四个单元的内容你去复习好它，这样家长期中考试咱没问题了到了期末只需要让孩子们会的一遍过，不会来的圈出来做专项",
              "timestamp": "[01:51 --> 02:08]"
            },
            {
              "type": "信任背书",
              "content": "都知道一本压题是很准的，你考试考到了这就是白给的分",
              "timestamp": "[02:21 --> 02:26]"
            },
            {
              "type": "服务保障",
              "content": "这里面我都给你带好了什么呀二维码免费的视频讲解咱带着孩子们去学去练家长们对吧",
              "timestamp": "[02:32 --> 02:42]"
            },
            {
              "type": "促销逼单",
              "content": "外边书店买这三颗要咱一百多今天来到官方店福利价格三颗到时候五十一块钱活动价格就这一波",
              "timestamp": "[02:44 --> 02:51]"
            },
            {
              "type": "版本说明",
              "content": "语文全国通用不用管数学我们是人教苏教北师英语只有三七点的人教PEP英语用不了的您就光拍语文数学这两本就可以了",
              "timestamp": "[00:18 --> 03:11]"
            },
            {
              "type": "考点赠送",
              "content": "所有买完这个卷子的家长们你带回家之后遇到不会的酥酥的题一定是考点没掌握好我给您送上李淑英三颗考点都在这了",
              "timestamp": "[00:28 --> 00:39]"
            }
          ]
        }
      ],
      "user_persona": "小学1-6年级学生家长，孩子即将面临期中/期末考试，面临复习时间紧、知识点变难、家长无法辅导等痛点，需要高效复习资料和便捷的辅导工具",
      "strategy_summary": "通过强调期中/期末考试时间紧迫（不到两周）制造焦虑，针对家长辅导不了孩子的痛点提供解决方案（免费视频讲解+考点资料），以51元三科的超值活动价吸引下单，配合多版本可选降低购买门槛，使用限时限量送考点资料逼单，整体形成「痛点激发→解决方案提供→价格引力→限时逼单」的完整销售闭环。",
      "highlights": [
        "主推品为教辅试卷套装而非课程，客单价低但覆盖全学科",
        "反复强调三重复习路径：单元卷查漏补缺→专项卷重点突破→真题压题",
        "赠送考点资料作为逼单手段，制造稀缺感",
        "强调「一本」品牌压题准确性建立信任",
        "多版本覆盖：语文全国通用/数学人教苏教北师/英语人教PEP，适应不同地区需求",
        "免费视频讲解解决家长辅导痛点"
      ]
    },
    {
      "session_id": 21,
      "competitor": "一本小学好书严选",
      "recorded_at": "2026-04-17 23:53:32.319583",
      "key_products": [
        {
          "name": "小学古诗词必背手册",
          "price": "29元",
          "selling_points": [
            "涵盖小学必考155首古诗词（75首课内+80首课外）",
            "完全同步孩子课本，按年级顺序划分",
            "彩色漫画图解+拼音+视频讲解，帮助孩子理解记忆",
            "思维导图+翻译注释，帮助孩子理解性背诵",
            "赠送默写本，检验背诵效果",
            "一年不到5元，可用六年"
          ],
          "scripts": [
            {
              "type": "痛点",
              "content": "你像现在小学阶段要求孩子必考的就这一百五十五首，七十五首是课内的八十首是课外，这里边全部都给你整理好了考不出这个范围所以考试考什么咱俩还得去背什么",
              "timestamp": "04:13-04:21"
            },
            {
              "type": "价值塑造",
              "content": "整个小学六年所有必考的古诗词都在这，从现在开始一直用到孩子小学毕业",
              "timestamp": "05:35-05:39"
            },
            {
              "type": "效果承诺",
              "content": "孩子真正理解了，你不到五分钟他自己就能背回一首诗",
              "timestamp": "01:49-01:51"
            },
            {
              "type": "信任背书",
              "content": "遇到任何不懂不明白，直接扫码都有一视频讲解，专业老师带着孩子学明白，家长不用去操心",
              "timestamp": "05:07-05:10"
            },
            {
              "type": "比喻说服",
              "content": "月落无题说满天，无题什么意思，江峰与火对窗明，江峰什么意思，与火是什么意思，他都是用漫画给你画出来，那孩子有兴趣他愿主动去看，而且一看就能看懂",
              "timestamp": "01:26-01:36"
            },
            {
              "type": "促销逼单",
              "content": "7点45之前拍的，那个是吧，还有最后的七分钟，7点45以前拍的，我全部送，7点45以后再来没有了，所以抓紧时间拼手做",
              "timestamp": "00:03-00:11"
            },
            {
              "type": "服务保障",
              "content": "现在拍下永久免费，随时扫码随时观看",
              "timestamp": "02:20-02:22"
            }
          ]
        }
      ],
      "user_persona": "幼儿园及小学生家长，孩子处于幼小衔接或小学阶段，家长焦虑孩子古诗词背诵问题，不知道该背什么、怎么背，担心孩子跟不上学校进度或考试丢分",
      "strategy_summary": "通过强调'考试必考'和'老师要求'制造家长焦虑，同时用'155首必考诗词'的精准范围解决'不知道背什么'的痛点；用漫画图解+视频讲解+拼音等降低孩子背诵难度；最后通过限时限量+赠品策略逼单，7点45分是关键时间节点",
      "highlights": [
        "强调7点45前发货是现货有视频讲解，7点45后预售视频讲解要收费，制造紧迫感",
        "赠送默写本作为检验背诵效果的配套工具，增加产品附加值",
        "原价比对：书店售价五六十元，直播间半价29元",
        "话术重复度高，多次循环讲解同一产品信息，覆盖不同进入直播间的观众"
      ]
    },
    {
      "session_id": 22,
      "competitor": "一本图书官方旗舰店小学",
      "recorded_at": "2026-04-17 23:53:32.861798",
      "key_products": [
        {
          "name": "一本图书·小学生作文套装（语文+英语）",
          "price": "61元两本",
          "selling_points": [
            "语文英语两本套装，涵盖作文写作方法与范文",
            "七大热点主题（机器人AI、国际油价上涨、美意战争等）",
            "带审题指导、写作框架、开头中间结尾思路",
            "好词好句彩色标注",
            "赠送免费外教音频",
            "原价100多元，直播间61元省一半",
            "背三篇作文考试50分轻松拿"
          ],
          "scripts": [
            {
              "type": "痛点",
              "content": "孩子是不需要再去死经背的孩子考试一套相类似的主题咱是不是拿回来咱就能直接用很简单对吧",
              "timestamp": "00:04 --> 00:12"
            },
            {
              "type": "价值塑造",
              "content": "包括说孩子肚子里眉毛水写作文一写流水帐大白话的好词好句都做好彩色标注比方说今年孩子考到机器是考到EI优美的学的背下来了",
              "timestamp": "00:14 --> 00:22"
            },
            {
              "type": "效果承诺",
              "content": "考试作文这30分的远分家长孩子也能变得更简单",
              "timestamp": "00:32 --> 00:37"
            },
            {
              "type": "信任背书",
              "content": "每个主题也是按照三不来包括说孩子英语有看不懂的地方家长您甭谈心每天放门旁边带好免费的外教银屏了",
              "timestamp": "00:42 --> 00:49"
            },
            {
              "type": "促销逼单",
              "content": "数量不多家长我单独给你申请的说过了就送到7点45最后5分钟时间家长拼手速5分钟之后您再来买咱是没有这两本热点话题的",
              "timestamp": "01:52 --> 02:04"
            },
            {
              "type": "价值塑造",
              "content": "一号链接两本大会就让孩子赶紧从现在开始咱就要背热点压剂作文要背咱就背有用的对吧",
              "timestamp": "02:36 --> 02:42"
            }
          ]
        },
        {
          "name": "热点话题作文（赠品）",
          "price": "0元（拍一号链接赠送）",
          "selling_points": [
            "国际油价上涨",
            "美意战争",
            "当下社会热点素材和范文",
            "拿回家重点背诵"
          ],
          "scripts": [
            {
              "type": "价值塑造",
              "content": "包括现在拍一号链接两本作文的家长我再给孩子送两本咱们的热点话题这个月刚给孩子做更新的国际油价上涨每一战争当下非常火的社会热点我全都给孩子带好私卡和发文了",
              "timestamp": "01:32 --> 01:42"
            },
            {
              "type": "效果承诺",
              "content": "因为你作文考到了孩子他才能会能说会写你作文这50份家长才相当于是白送给您的",
              "timestamp": "01:44 --> 01:52"
            },
            {
              "type": "促销逼单",
              "content": "数量不多家长我单独给你申请的说过了就送到7点45最后5分钟时间家长拼手速",
              "timestamp": "01:52 --> 01:58"
            }
          ]
        }
      ],
      "user_persona": "六年级小学生家长，孩子即将面临小学毕业考试，语文英语作文占试卷50分，家长希望孩子作文提分但孩子写作文流水账大白话、肚里没墨水，家长不愿花三五千报英语班",
      "strategy_summary": "围绕小学毕业考试作文50分占比高的痛点，强调新课标规定考热点话题，通过考前背诵积累提分的方法论，配合低价61元两本、赠品饥饿营销、限时限量逼单策略，推动家长下单。",
      "highlights": [
        "主推一号链接作文套装，定价61元两本（原价100多元），强调省一半",
        "赠品两本热点话题只送到7点45，利用时间紧迫感逼单",
        "反复强调新课标规定作文考热点话题，增强权威性",
        "强调免费外教音频，替代线下三五千英语班",
        "针对六年级家长，强调最后40多天毕业考试、8天假期可利用"
      ]
    }
  ]
}