{
  "dates": [
    "2026-06-25",
    "2026-04-14",
    "2026-04-13"
  ],
  "latest_day": "2026-06-25",
  "competitors_on_day": [
    {
      "session_id": 19,
      "competitor": "一本小学好书推荐",
      "recorded_at": "2026-06-25 00:25:19.100208",
      "key_products": [
        {
          "name": "一本·小学总复习三件套（语文+数学+英语）",
          "price": "89元三本",
          "selling_points": [
            "2026年最新改版",
            "不分版本全国通用",
            "包含小学六年所有公式定理、单词语法、高频考点",
            "买三本额外赠送三本练习题",
            "已售130多万套",
            "七天无理由退货"
          ],
          "scripts": [
            {
              "type": "开场/暖场",
              "content": "五生六的家长看这了，这个暑假你什么都不干，一定要做复习，因为孩子明年就要上初中了",
              "timestamp": "[00:17 --> 00:18]"
            },
            {
              "type": "痛点",
              "content": "到六年级又写新课又总复习，堆到一些孩子压力大，没有时间没有精力",
              "timestamp": "[00:33 --> 00:37]"
            },
            {
              "type": "价值塑造",
              "content": "语文：整个小学六年所有课内外的字音字形古诗文、阅读理解作文、成语百科都给你带着；数学：所有公式定理都在这；英语：所有单词语法加时态都在这里",
              "timestamp": "[02:52 --> 04:00]"
            },
            {
              "type": "价值塑造",
              "content": "六年高频考点做好了标记，哪里是重点一目了然，让孩子重点学重点背",
              "timestamp": "[03:29 --> 03:35]"
            },
            {
              "type": "信任背书",
              "content": "这套书卖了130多万套，内容质量非常好",
              "timestamp": "[00:50 --> 00:55]"
            },
            {
              "type": "信任背书",
              "content": "我们一本家专业做教辅将近快20年了，质量内容售后有保障",
              "timestamp": "[07:20 --> 07:24]"
            },
            {
              "type": "效果承诺",
              "content": "五升六的买一号链接，暑假一定要提前让孩子复习复习，为孩子减轻下压力，明年才能更好做衔接",
              "timestamp": "[05:38 --> 05:47]"
            },
            {
              "type": "促销逼单",
              "content": "三本书半价89块钱，保证正版保证最新版，8点15打包发快递",
              "timestamp": "[00:38 --> 00:46]"
            },
            {
              "type": "促销逼单",
              "content": "今天在我直播间拍下一号链接的，拍了三本的，我们再额外加送三本练习题",
              "timestamp": "[01:11 --> 01:15]"
            },
            {
              "type": "服务保障",
              "content": "七天无理由退货，如果大家实在担心，你可以都拿回家对比一下",
              "timestamp": "[00:54 --> 00:58]"
            }
          ]
        }
      ],
      "user_persona": "五升六、六年级学生及家长，孩子即将面临小升初考试，需要进行系统总复习，暑假是复习黄金期，但孩子课业压力大、时间紧张，需要高效、全面的复习资料",
      "strategy_summary": "围绕五升六学生小升初备考需求，强调暑假复习的紧迫性和重要性；通过突出产品包含六年全部知识点、高频考点标注、不分版本全国通用等卖点塑造产品价值；利用130万套销量、20年教辅经验进行信任背书；配合限时半价89元、买三送三练习题、8点15分截止等促销逼单手段促进下单",
      "highlights": [
        "主推一号链接三件套，强调语文数学英语三科全覆盖，不分版本全国通用",
        "买三本额外赠送三本练习题，实现学练结合",
        "反复强调五升六关键节点，备考小升初的紧迫性",
        "限时促销营造紧张感，8点15分打包发快递",
        "2026年最新改版作为重要卖点强调",
        "高频考点标注，帮助孩子有重点地复习"
      ]
    },
    {
      "session_id": 20,
      "competitor": "一本图书官方旗舰店小学",
      "recorded_at": "2026-06-25 00:25:19.595598",
      "key_products": [
        {
          "name": "小学教辅书套装（一号）",
          "price": "73元三科",
          "selling_points": [
            "最新改版版，与9月开学新课本同步",
            "包含课本全文、课后一类字二类字组词、练习题",
            "配套视频讲解，每课从头讲到尾",
            "六周42天学习规划，不用担心学不完",
            "不用另外买课本和练习册，一本书搞定",
            "语文全国统一版本，数学三种版本（人教/苏教/北师），英语两种版本（人教/译林）"
          ],
          "scripts": [
            {
              "type": "暖场/开场",
              "content": "不会选版本的看我这，你看那公平等版本的，当然等半天了，你不会怕的，我教你一家长",
              "timestamp": "00:00-00:07"
            },
            {
              "type": "痛点/需求引导",
              "content": "孩子是小学吗，是小学就点开一号，上选九月开学的年级，下面选版本",
              "timestamp": "00:07-00:10"
            },
            {
              "type": "价值塑造",
              "content": "看一下孩子的课本封面，知道版本再来拍。数学人教苏教北师，咱家只做了这三版本。英语只做了这两个，都是三起点的，人教版一林版",
              "timestamp": "00:13-00:21"
            },
            {
              "type": "信任背书",
              "content": "语文全国都一样，能明白咋拍了吧。然后咱都是最新版的",
              "timestamp": "00:26-00:32"
            },
            {
              "type": "产品介绍",
              "content": "首先不用担心孩子假期学不完，六周42天书有规划，你就跟着计划走，您放心他一定能学完。咱能学多少，整个新版上课的八个单元，课本的每一课都预习到，连语文原地都在，它非常全",
              "timestamp": "02:18-02:29"
            },
            {
              "type": "价值塑造",
              "content": "您拿回家什么课本练习课都不用买了，一本书搞定。我给您看一下，先学新版课本的课文全文，课后一类字二类字组词，课本有啥咱有啥才放里面呢，连这个图都一样",
              "timestamp": "02:33-02:43"
            },
            {
              "type": "服务保障",
              "content": "咱不会的，还有视频讲解，每一课讲课本讲细节，从头讲到尾，每天都是这样的",
              "timestamp": "02:53-02:59"
            },
            {
              "type": "促销逼单",
              "content": "今天活动满结束，拍一号套装加单，两本三本带着，我加赠一份赠品，只要不是拍单本，我都能给您赠",
              "timestamp": "00:34-00:40"
            },
            {
              "type": "促销逼单",
              "content": "咱是最后一批现货了，你看一号爆仓了，现在2500单，拍的抓紧，趁着现货下单，拿回家视频孩子才能免费去看",
              "timestamp": "07:13-07:18"
            },
            {
              "type": "促销逼单",
              "content": "三颗下输的150，今天不要，1号三颗官方卖价73，三门带走正经保障",
              "timestamp": "07:35"
            }
          ]
        }
      ],
      "user_persona": "小学二至六年级学生家长，孩子9月开学升年级，需要暑假预习辅导。家长关注孩子教材版本问题（数学、英语版本多），关心是否能与新学期课本同步，担忧孩子假期学不完或需要额外购买课本练习册。",
      "strategy_summary": "通过强调产品与9月开学新课本完全同步、包含完整课本内容+练习题+视频讲解、解决家长版本选择困惑，配合限时限量赠品促销和最后一批现货的紧迫感，促成家长下单购买。整体策略以产品实用性为核心，以促销紧迫感为推动力。",
      "highlights": [
        "价格锚定：73元三科对比官方售价，强调性价比",
        "赠品策略：暑假复习资料纸质版仅57份，制造稀缺紧迫感",
        "库存紧张：多次强调'爆仓'、'2500单'、'最后一批现货'逼单",
        "版本说明详细：数学三版本、英语两版本、语文全国统一，反复讲解消除疑虑",
        "视频免费看：仅限下单客户，暗示错过再买需付费"
      ]
    },
    {
      "session_id": 21,
      "competitor": "一本小学好物推荐",
      "recorded_at": "2026-06-25 00:25:24.681305",
      "key_products": [
        {
          "name": "一本小学考点速记（语数英三科合订本）",
          "price": "34元/三本，10元/单本",
          "selling_points": [
            "语数英三科全覆盖，一本书包含全部重点",
            "完全同步最新版教材，保障是改版后最新版本",
            "暑假提前背重点，开学减轻压力",
            "赠送红膜自测，哪里不会一目了然",
            "赠送三科练习册，包含单元测、专项题、考点测试",
            "书店原价六七十元，直播间半价仅10元"
          ],
          "scripts": [
            {
              "type": "开场/暖场",
              "content": "来今天拍的我都不让你摆来，背完了之后一定要做题巩固",
              "timestamp": "00:00-00:02"
            },
            {
              "type": "痛点",
              "content": "一个孩子九月份升年级，你要背的会更难，但是课本上没有重点啊",
              "timestamp": "00:33-00:36"
            },
            {
              "type": "价值塑造",
              "content": "语书英三科都在这一本书上，完全同步最新版教材，保证新版，暑假提前背重点啊，今学期你会特别简单",
              "timestamp": "00:41-00:48"
            },
            {
              "type": "产品展示",
              "content": "怎么用来看语文啊，考啥背啥，一类字二类字多音字，词理解背诵段落整理好了，基础分咱是不能丢的",
              "timestamp": "00:50-00:54"
            },
            {
              "type": "痛点放大",
              "content": "分析句子课本里剪，课本上没有，但是考试30分你不能丢了",
              "timestamp": "00:58-01:01"
            },
            {
              "type": "信任背书",
              "content": "官方指不见这本书保证最新版的啊",
              "timestamp": "00:28-00:32"
            },
            {
              "type": "效果承诺",
              "content": "每天十分钟背完，来期学期咱就不用再熬夜了",
              "timestamp": "02:38-02:40"
            },
            {
              "type": "促销逼单",
              "content": "你书店买的话都留期时，今天十块钱一颗，三颗三十四代付价，还给你送联系",
              "timestamp": "01:45-01:51"
            },
            {
              "type": "服务保障",
              "content": "放心去拍放去在官方直播间发货啊",
              "timestamp": "01:39-01:42"
            },
            {
              "type": "痛点",
              "content": "因为所有小学生，还在九月份，你要升年级，要背的会更难，但课本上没有终点",
              "timestamp": "04:24-04:30"
            },
            {
              "type": "促销逼单",
              "content": "每个年级现在就还有九份了，每个年级就还有九份，赶得上的下单",
              "timestamp": "04:04-04:08"
            }
          ]
        }
      ],
      "user_persona": "小学一年级至六年级学生家长，孩子将于9月份升入新年级，面临学习难度提升和暑期复习巩固需求。痛点在于：课本上没有考试重点、孩子暑假不知道该背什么、担心开学后学习压力大、担心孩子开学后知识遗忘。",
      "strategy_summary": "采用「痛点+解决方案+价值塑造+促销逼单」的话术策略。首先通过「升年级难度增加+课本无重点」激发家长焦虑，然后推出「考点速记」一站式解决方案，强调三科全覆盖、同步新教材、包含考试重点（尤其是30分的句子分析题），再通过半价促销（10元vs书店60-70元）、限量赠品（红膜+练习册）、限时限量逼单促成转化。",
      "highlights": [
        "直播间实时显示剩余库存（17份→11份→9份），营造稀缺紧迫感",
        "多次强调「最新版」「官方直播间发货」建立信任",
        "赠送红膜解决「背完不会检测」的痛点，实现自测功能",
        "强调「三合一」书籍，一本抵三本，性价比高",
        "针对版本问题提供解决方案：按数学版本下单即可",
        "多次引导已拍用户「留好以拍」，强调售后服务"
      ]
    },
    {
      "session_id": 22,
      "competitor": "一本小学好书严选",
      "recorded_at": "2026-06-25 00:25:25.088373",
      "key_products": [
        {
          "name": "小学一年级语文数学套装",
          "price": "49元",
          "selling_points": [
            "两本套装全国通用",
            "赠送1300字识字表",
            "赠送英语书（字母+单词+外教音频）",
            "赠送免费视频讲解（价值3000元）",
            "42天暑假学习计划",
            "课本+练习册一体，无需单独买课本"
          ],
          "scripts": [
            {
              "type": "痛点",
              "content": "如果孩子识字量不够的话，你看着他肯定是赶不上的，你看课本都跟看天书一样的，孩子根本就跟不上啊",
              "timestamp": "08:17-08:23"
            },
            {
              "type": "价值塑造",
              "content": "你现在大单我给你送上免费的诗名讲解，咱抢到之后省价格三四千块钱没问题",
              "timestamp": "06:30-06:34"
            },
            {
              "type": "促销逼单",
              "content": "只有你现在拍的才有，现在拍下我给你送上1300字数字表",
              "timestamp": "00:28-00:34"
            },
            {
              "type": "服务保障",
              "content": "永久免费，没有任何的二次交费",
              "timestamp": "08:44-08:45"
            }
          ]
        }
      ],
      "user_persona": "9月份即将上小学一年级的孩子家长，面临幼小衔接焦虑，担心孩子入学后跟不上进度，识字量不足，看不懂课本，需要提前预习语文数学英语科目。",
      "strategy_summary": "通过强调幼小衔接的紧迫性和小学与幼儿园的巨大差异制造焦虑，突出产品包含语文数学英语全科教材+练习册+1300字识字表+视频讲解的高性价比，强调现在下单可省3000元培训费，用限时限量赠品策略和倒计时逼单促进转化。",
      "highlights": [
        "价格极低：49元两本套装还送1300元赠品（识字表+英语书+视频讲解），明显低于正常市场价",
        "赠品价值高：1300字识字表直击识字量痛点，英语书包含外教音频",
        "强调时间紧迫：反复使用8点15/8点20倒计时，制造紧迫感",
        "痛点精准：抓住家长担心孩子上小学后跟不上的焦虑心理",
        "服务保障明确：永久免费无二次交费，降低家长决策成本"
      ]
    },
    {
      "session_id": 23,
      "competitor": "一本官方旗舰店小学",
      "recorded_at": "2026-06-25 00:25:25.241217",
      "key_products": [
        {
          "name": "一本·初中文言文古诗词合集",
          "price": "31元",
          "selling_points": [
            "全国通用部分版本，2026年新版教材同步",
            "包含87首古诗词+39篇文言文，共126篇",
            "每节课配套动画视频激发兴趣",
            "漫画解释重点字词，全文带翻译",
            "思维导图帮助背诵，防止遗忘",
            "考试真题练习，暑假提前背诵，开学更轻松",
            "适合3-9年级（7个年级）"
          ],
          "scripts": [
            {
              "type": "痛点",
              "content": "咱们的孩子现在上六年级的，你一定要自己听，小生出这个暑假，一定要孩子把这个文言文给他提前背过，因为咱们的孩子上了初中之后，文言文占60分，而且孩子从三科变七科，时间又紧张又大，那孩子写完作业之后，都已经十一二点了，根本没有时间提前学习",
              "timestamp": "00:40-00:57"
            },
            {
              "type": "价值塑造",
              "content": "让孩子提前背过之后，开学会更加轻松，也不用提前熬大夜",
              "timestamp": "00:57-01:02"
            },
            {
              "type": "开场",
              "content": "来首先孩子没学过会吗，咱们都有一个免费的视频，带着孩子去学",
              "timestamp": "00:02-00:07"
            },
            {
              "type": "信任背书",
              "content": "你去问一下咱们的小科服，五四支可以用吗，因为老师也不太具体的，也不太了解，是通用的，是全国通用的",
              "timestamp": "00:11-00:25"
            },
            {
              "type": "内容介绍",
              "content": "初中三年必备的87首古诗词，39篇文言文，老师都按照年纪数据给你括好了，一共就是这126篇，咱考试就考这些，也是咱们初中老师要求全篇背诵的",
              "timestamp": "01:17-01:30"
            },
            {
              "type": "学习方式",
              "content": "孩子一看就不愿意学，没有兴趣，你去拍拍之后，先让孩子去看这个免费的动画片，孩子一看理解了，自然而然就愿意学",
              "timestamp": "01:35-01:45"
            },
            {
              "type": "促销逼单",
              "content": "平时外面六十多一本，今天在老师直播间里面啊，老师直接给你三十一块钱，给你包送到家了",
              "timestamp": "02:57-03:02"
            },
            {
              "type": "赠品策略",
              "content": "只要是今天拍下的家长，我都额外赠送给你一份免费的视频家家打卡单，给咱们专业的老师，带着孩子进行一个背诵",
              "timestamp": "03:03-03:09"
            },
            {
              "type": "稀缺营造",
              "content": "还有最后六单，六单之后你再来拍没有任何东西了",
              "timestamp": "00:00-00:02"
            }
          ]
        }
      ],
      "user_persona": "小升初及初中学生家长（主要针对6年级即将升初中的孩子），孩子即将面临初中学习压力增大（从三科变七科），文言文占比高（60分），作业多、时间紧张，家长希望孩子暑假提前背诵文言文古诗词，开学后学习更轻松",
      "strategy_summary": "以小升初痛点切入，强调初中文言文60分占比和学业压力大的现实，通过动画视频、漫画、思维导图等趣味学习方式解决孩子不爱学的问题，利用限时限量（最后6单）+低价（31元 vs 60多元）+赠品策略逼单，同时强调正品保障消除购买顾虑",
      "highlights": [
        "强调'最后6单'的稀缺性营造紧迫感",
        "原价60多元，直播间31元，价格反差大",
        "赠品（视频打卡单）作为额外刺激，强调老师带打卡解决家长辅导难题",
        "针对6年级家长反复强调暑假提前准备的重要性",
        "多处强调全国通用、部分版本可用，解答家长版本顾虑",
        "信任背书：正品保证、7天无理由退换"
      ]
    },
    {
      "session_id": 24,
      "competitor": "一本官方旗舰店",
      "recorded_at": "2026-06-25 00:25:25.262701",
      "key_products": [
        {
          "name": "一本官方旗舰店·暑假作业三件套（数学口算+语文练字+阅读理解）",
          "price": "70元",
          "selling_points": [
            "每天三件事练明白提分",
            "数学口算培养计算思维和应用题能力",
            "语文练字涵盖新学期八个单元必考笔顺笔画和古诗文",
            "阅读理解针对40分大题",
            "完全同步2026新版教材",
            "拍三本送英语单词语法句子纸质版",
            "每道题赠送视频讲解",
            "现货秒发，明后天收货"
          ],
          "scripts": [
            {
              "type": "价值塑造",
              "content": "每天三件事练明白提分，第一复习预习都带着，先讲书再讲版本，看数学，名字叫口算，口算比算辨识算应用其数学思维，每天十分钟练的一面，计算思维能力练上来，新学期数学越学越简单",
              "timestamp": "00:00-00:18"
            },
            {
              "type": "价值塑造",
              "content": "看字片，里边练的就是新学期八个单元，每节课必考的笔顺笔画组成，为你做梦想的古书本，用好的一本，把字写好的同时，基础30分不会再丢",
              "timestamp": "00:18-00:28"
            },
            {
              "type": "价值塑造",
              "content": "最后看阅读，课外阅读理解，家长大提40分，生的年纪更难，随暑假重点练，那么礼拜选的文章也都是这种孩子感兴趣的愿意看，那么能坚持",
              "timestamp": "00:29-00:40"
            },
            {
              "type": "促销逼单",
              "content": "一号链接都是现货，三本现货抢到，每一道题给你送书名讲解，马上8点15关于寿，来的晚预售，他就要收费了，一定现在拍",
              "timestamp": "00:43-00:51"
            },
            {
              "type": "价格锚点",
              "content": "然后你去书店买的话，家长这三本都100多，今天官方开办改，其实听明白的，点开一号链接，选好三本下单",
              "timestamp": "00:51-00:58"
            },
            {
              "type": "服务保障",
              "content": "拍的几年纪告诉我，别拍完，来得早家长，语文数学拍了，只要拍了三本，我就给你送英语，新学习来英语的单词、语法句子全在这，拿回家让孩子练起来",
              "timestamp": "01:12-01:23"
            },
            {
              "type": "促销逼单",
              "content": "送英语这样，都是纸质版，纸质版单独加印的，那8点15节呢，来的晚可不送了，你电子版自个打印，拼头速吧",
              "timestamp": "01:26-01:32"
            }
          ]
        },
        {
          "name": "赠品·英语单词语法句子纸质版",
          "price": "拍三本即赠送",
          "selling_points": [
            "新学期英语单词语法句子全覆盖",
            "纸质版单独加印",
            "仅限8点15前下单赠送",
            "拍几年级送几年级"
          ],
          "scripts": [
            {
              "type": "促销逼单",
              "content": "你拍几年级我送几年级，送的英语这样，都是纸质版，纸质版单独加印的，那8点15节呢，来的晚可不送了",
              "timestamp": "01:23-01:30"
            }
          ]
        }
      ],
      "user_persona": "1-6年级小学生家长，孩子即将升小学或处于小学阶段，面临暑假作业安排和学科辅导需求，痛点是孩子数学计算能力弱、语文基础（字词）容易丢分、阅读理解能力差，希望通过暑假自主练习提升成绩",
      "strategy_summary": "采用'三件事提分'框架系统化推销，围绕数学思维、语文基础、阅读理解三大痛点展开，通过限时限量促销（8点15分截止、现货限量）制造紧迫感，利用价格锚点（原價100多→现价70）和买三赠一策略提升客单价，同时用视频讲解赠送替代高价数学培训班来塑造性价比",
      "highlights": [
        "直播间多次强调8点15分截止促销，制造稀缺紧迫感",
        "拍三本赠送英语纸质版是核心促销手段，限时限量",
        "话术结构清晰：先讲产品价值→再给价格优惠→最后限时逼单，循环重复多遍",
        "反复强调'现货''明后天收货'解决家长对发货时间的担忧",
        "针对不同科目给出不同版本选择说明（语文通用，数学四选一）",
        "全程未提及具体商品SKU细节如出版社、页数等，以功能性描述为主"
      ]
    }
  ]
}